LICENSE.txt
MANIFEST.in
README.md
VERSION
pypdnsrest.py
setup.py
pypdnsrest/__init__.py
pypdnsrest/client.py
pypdnsrest/dnsrecords.py
pypdnsrest/dnszone.py
pypdnsrest/parsers.py
pypdnsrest.egg-info/PKG-INFO
pypdnsrest.egg-info/SOURCES.txt
pypdnsrest.egg-info/dependency_links.txt
pypdnsrest.egg-info/entry_points.txt
pypdnsrest.egg-info/not-zip-safe
pypdnsrest.egg-info/requires.txt
pypdnsrest.egg-info/top_level.txt