Metadata-Version: 1.1
Name: pypdnsrest
Version: 2018.2.17.161125
Summary: PowerDNS REST API Client
Home-page: https://github.com/raspi/pypdnsrest
Author: Pekka Järvinen
Author-email: pekka.jarvinen@gmail.com
License: Apache 2.0
Keywords: dns powerdns pdns rest api web python http
Platform: UNKNOWN
Classifier: Development Status :: 3 - Alpha
Classifier: Intended Audience :: Developers
Classifier: Programming Language :: Python :: 3.5
Classifier: Topic :: Internet :: WWW/HTTP
Classifier: Operating System :: POSIX :: Linux
Classifier: Topic :: Software Development :: Libraries
Classifier: Topic :: System :: Networking
